tiramisu_wallet_client/__init__.py
tiramisu_wallet_client/temp.png
tiramisu_wallet_client/test.py
tiramisu_wallet_client/tiramisu_client.py
tiramisu_wallet_client-0.0.8.dist-info/METADATA
tiramisu_wallet_client-0.0.8.dist-info/WHEEL
tiramisu_wallet_client-0.0.8.dist-info/licenses/LICENSE
tiramisu_wallet_client-0.0.8.dist-info/RECORD
