Metadata-Version: 2.3
Name: tiramisu-wallet-client
Version: 0.0.8
Summary: A client for Tiramisu wallet platform. This client allows you to programatically mint, transfer and trade Taproot Assets Protocol that represents altcoins and NTFs on Bitcoin blackchain. 
Project-URL: Homepage, https://github.com/snow884/tiramisu_wallet_client
Project-URL: Bug Tracker, https://github.com/snow884/tiramisu_wallet_client/issues
Author-email: Adam Ivansky <adam.ivansky@gmail.com>
License-File: LICENSE
Classifier: License :: OSI Approved :: MIT License
Classifier: Operating System :: OS Independent
Classifier: Programming Language :: Python :: 3
Requires-Python: >=3.7
Requires-Dist: requests>=2.6.1
